{
  "metadata": {
    "ticker": "ASTX",
    "generated_at": "2026-02-26T01:33:01.928293+00:00Z",
    "date_range": "2025-11-27 to 2026-02-25",
    "source": "volumeleaders.com",
    "script": "populate_ticker_data.py"
  },
  "prints": [
    {
      "timestamp": 1771905600,
      "price": 39.1,
      "volume": 321498,
      "dollars": 12570571,
      "rank": 1,
      "conditions": "",
      "exchange": "",
      "is_dark_pool": false,
      "relative_size": 0.0,
      "vcd": 0.0
    },
    {
      "timestamp": 1770696000,
      "price": 61.29,
      "volume": 84518,
      "dollars": 5180108,
      "rank": 2,
      "conditions": "",
      "exchange": "",
      "is_dark_pool": false,
      "relative_size": 0.0,
      "vcd": 0.0
    },
    {
      "timestamp": 1770177600,
      "price": 62.94,
      "volume": 79618,
      "dollars": 5011156,
      "rank": 3,
      "conditions": "",
      "exchange": "",
      "is_dark_pool": false,
      "relative_size": 0.0,
      "vcd": 0.0
    },
    {
      "timestamp": 1770350400,
      "price": 69.21,
      "volume": 61350,
      "dollars": 4246039,
      "rank": 5,
      "conditions": "",
      "exchange": "",
      "is_dark_pool": false,
      "relative_size": 0.0,
      "vcd": 0.0
    },
    {
      "timestamp": 1767844800,
      "price": 61.7,
      "volume": 61057,
      "dollars": 3767216,
      "rank": 6,
      "conditions": "",
      "exchange": "",
      "is_dark_pool": false,
      "relative_size": 0.0,
      "vcd": 0.0
    },
    {
      "timestamp": 1769400000,
      "price": 81.2,
      "volume": 45788,
      "dollars": 3717985,
      "rank": 7,
      "conditions": "",
      "exchange": "",
      "is_dark_pool": false,
      "relative_size": 0.0,
      "vcd": 0.0
    },
    {
      "timestamp": 1769486400,
      "price": 74.0,
      "volume": 46285,
      "dollars": 3425090,
      "rank": 8,
      "conditions": "",
      "exchange": "",
      "is_dark_pool": false,
      "relative_size": 0.0,
      "vcd": 0.0
    },
    {
      "timestamp": 1768363200,
      "price": 61.0,
      "volume": 50000,
      "dollars": 3050000,
      "rank": 10,
      "conditions": "",
      "exchange": "",
      "is_dark_pool": false,
      "relative_size": 0.0,
      "vcd": 0.0
    },
    {
      "timestamp": 1768190400,
      "price": 65.0,
      "volume": 44500,
      "dollars": 2892500,
      "rank": 12,
      "conditions": "",
      "exchange": "",
      "is_dark_pool": false,
      "relative_size": 0.0,
      "vcd": 0.0
    },
    {
      "timestamp": 1769140800,
      "price": 92.13,
      "volume": 30156,
      "dollars": 2778272,
      "rank": 13,
      "conditions": "",
      "exchange": "",
      "is_dark_pool": false,
      "relative_size": 0.0,
      "vcd": 0.0
    }
  ],
  "levels": [
    {
      "price": 39.1,
      "volume": 321498,
      "dollars": 12570571,
      "rank": 1
    },
    {
      "price": 62.9,
      "volume": 132970,
      "dollars": 8366279,
      "rank": 2
    },
    {
      "price": 94.0,
      "volume": 80000,
      "dollars": 7520000,
      "rank": 3
    },
    {
      "price": 61.0,
      "volume": 117055,
      "dollars": 7141254,
      "rank": 4
    },
    {
      "price": 61.3,
      "volume": 113256,
      "dollars": 6942609,
      "rank": 5
    }
  ],
  "boxes": []
}