{
  "metadata": {
    "ticker": "ATGE",
    "generated_at": "2025-07-25T01:14:37.296888+00:00Z",
    "date_range": "2025-04-25 to 2025-07-24",
    "source": "volumeleaders.com",
    "script": "populate_ticker_data.py"
  },
  "prints": [
    {
      "timestamp": 1750392000,
      "price": 125.08,
      "volume": 409382,
      "dollars": 51205500,
      "rank": 10,
      "conditions": "",
      "exchange": "",
      "is_dark_pool": false,
      "relative_size": 0.0,
      "vcd": 0.0
    },
    {
      "timestamp": 1750996800,
      "price": 128.49,
      "volume": 382522,
      "dollars": 49150251,
      "rank": 11,
      "conditions": "",
      "exchange": "",
      "is_dark_pool": false,
      "relative_size": 0.0,
      "vcd": 0.0
    },
    {
      "timestamp": 1750996800,
      "price": 128.49,
      "volume": 298928,
      "dollars": 38409258,
      "rank": 12,
      "conditions": "",
      "exchange": "",
      "is_dark_pool": false,
      "relative_size": 0.0,
      "vcd": 0.0
    }
  ],
  "levels": [
    {
      "price": 128.5,
      "volume": 1010000,
      "dollars": 130000000,
      "rank": "4"
    },
    {
      "price": 125.1,
      "volume": 440000,
      "dollars": 60000000,
      "rank": "19"
    },
    {
      "price": 129.7,
      "volume": 230000,
      "dollars": 30000000,
      "rank": "82"
    },
    {
      "price": 136.3,
      "volume": 190000,
      "dollars": 30000000,
      "rank": "94"
    },
    {
      "price": 127.6,
      "volume": 200000,
      "dollars": 30000000,
      "rank": "0"
    }
  ],
  "boxes": []
}