{
  "metadata": {
    "ticker": "CRDO",
    "generated_at": "2025-11-19T21:10:47.816648+00:00Z",
    "date_range": "2025-08-21 to 2025-11-19",
    "source": "volumeleaders.com",
    "script": "populate_ticker_data.py"
  },
  "prints": [
    {
      "timestamp": 1758254400,
      "price": 169.56,
      "volume": 7651664,
      "dollars": 1297416147,
      "rank": 1,
      "conditions": "",
      "exchange": "",
      "is_dark_pool": false,
      "relative_size": 0.0,
      "vcd": 0.0
    },
    {
      "timestamp": 1760068800,
      "price": 138.83,
      "volume": 1479726,
      "dollars": 205430360,
      "rank": 2,
      "conditions": "",
      "exchange": "",
      "is_dark_pool": false,
      "relative_size": 0.0,
      "vcd": 0.0
    },
    {
      "timestamp": 1756180800,
      "price": 120.1,
      "volume": 1367192,
      "dollars": 164199759,
      "rank": 3,
      "conditions": "",
      "exchange": "",
      "is_dark_pool": false,
      "relative_size": 0.0,
      "vcd": 0.0
    },
    {
      "timestamp": 1757476800,
      "price": 163.96,
      "volume": 866864,
      "dollars": 142131021,
      "rank": 5,
      "conditions": "",
      "exchange": "",
      "is_dark_pool": false,
      "relative_size": 0.0,
      "vcd": 0.0
    },
    {
      "timestamp": 1762315200,
      "price": 173.16,
      "volume": 760624,
      "dollars": 131709651,
      "rank": 6,
      "conditions": "",
      "exchange": "",
      "is_dark_pool": false,
      "relative_size": 0.0,
      "vcd": 0.0
    },
    {
      "timestamp": 1759291200,
      "price": 144.91,
      "volume": 882752,
      "dollars": 127919592,
      "rank": 8,
      "conditions": "",
      "exchange": "",
      "is_dark_pool": false,
      "relative_size": 0.0,
      "vcd": 0.0
    },
    {
      "timestamp": 1759982400,
      "price": 151.15,
      "volume": 828869,
      "dollars": 125283549,
      "rank": 9,
      "conditions": "",
      "exchange": "",
      "is_dark_pool": false,
      "relative_size": 0.0,
      "vcd": 0.0
    },
    {
      "timestamp": 1761278400,
      "price": 155.55,
      "volume": 772323,
      "dollars": 120134842,
      "rank": 10,
      "conditions": "",
      "exchange": "",
      "is_dark_pool": false,
      "relative_size": 0.0,
      "vcd": 0.0
    },
    {
      "timestamp": 1760328000,
      "price": 149.9,
      "volume": 761176,
      "dollars": 114100282,
      "rank": 11,
      "conditions": "",
      "exchange": "",
      "is_dark_pool": false,
      "relative_size": 0.0,
      "vcd": 0.0
    },
    {
      "timestamp": 1763352000,
      "price": 145.58,
      "volume": 767969,
      "dollars": 111800927,
      "rank": 12,
      "conditions": "",
      "exchange": "",
      "is_dark_pool": false,
      "relative_size": 0.0,
      "vcd": 0.0
    }
  ],
  "levels": [
    {
      "price": 169.6,
      "volume": 8590000,
      "dollars": 1460000000,
      "rank": "1"
    },
    {
      "price": 138.8,
      "volume": 1910000,
      "dollars": 270000000,
      "rank": "2"
    },
    {
      "price": 164.0,
      "volume": 1430000,
      "dollars": 230000000,
      "rank": "6"
    },
    {
      "price": 145.6,
      "volume": 1500000,
      "dollars": 220000000,
      "rank": "7"
    },
    {
      "price": 144.9,
      "volume": 1440000,
      "dollars": 210000000,
      "rank": "8"
    }
  ],
  "boxes": []
}