{
  "metadata": {
    "ticker": "ESTC",
    "generated_at": "2026-02-21T01:37:04.359932+00:00Z",
    "date_range": "2025-11-22 to 2026-02-20",
    "source": "volumeleaders.com",
    "script": "populate_ticker_data.py"
  },
  "prints": [],
  "levels": [
    {
      "price": 77.6,
      "volume": 3109251,
      "dollars": 241271059,
      "rank": 4
    },
    {
      "price": 76.4,
      "volume": 3085418,
      "dollars": 235731180,
      "rank": 5
    },
    {
      "price": 74.7,
      "volume": 2740329,
      "dollars": 204636134,
      "rank": 7
    },
    {
      "price": 76.2,
      "volume": 2581641,
      "dollars": 196703422,
      "rank": 11
    },
    {
      "price": 63.6,
      "volume": 3065309,
      "dollars": 194904651,
      "rank": 13
    }
  ],
  "boxes": []
}