{
  "metadata": {
    "ticker": "ETHE",
    "generated_at": "2025-08-26T21:12:53.862814+00:00Z",
    "date_range": "2025-05-28 to 2025-08-26",
    "source": "volumeleaders.com",
    "script": "populate_ticker_data.py"
  },
  "prints": [
    {
      "timestamp": 1755230400,
      "price": 36.36,
      "volume": 1300000,
      "dollars": 47268000,
      "rank": 6,
      "conditions": "",
      "exchange": "",
      "is_dark_pool": false,
      "relative_size": 0.0,
      "vcd": 0.0
    },
    {
      "timestamp": 1755576000,
      "price": 34.04,
      "volume": 1070000,
      "dollars": 36422800,
      "rank": 10,
      "conditions": "",
      "exchange": "",
      "is_dark_pool": false,
      "relative_size": 0.0,
      "vcd": 0.0
    },
    {
      "timestamp": 1754020800,
      "price": 29.13,
      "volume": 1020000,
      "dollars": 29712600,
      "rank": 17,
      "conditions": "",
      "exchange": "",
      "is_dark_pool": false,
      "relative_size": 0.0,
      "vcd": 0.0
    },
    {
      "timestamp": 1755489600,
      "price": 35.34,
      "volume": 777747,
      "dollars": 27485578,
      "rank": 20,
      "conditions": "",
      "exchange": "",
      "is_dark_pool": false,
      "relative_size": 0.0,
      "vcd": 0.0
    }
  ],
  "levels": [
    {
      "price": 28.1,
      "volume": 4000000,
      "dollars": 110000000,
      "rank": "1"
    },
    {
      "price": 27.8,
      "volume": 3760000,
      "dollars": 100000000,
      "rank": "2"
    },
    {
      "price": 27.7,
      "volume": 3310000,
      "dollars": 90000000,
      "rank": "3"
    },
    {
      "price": 26.5,
      "volume": 3390000,
      "dollars": 90000000,
      "rank": "4"
    },
    {
      "price": 22.2,
      "volume": 4040000,
      "dollars": 90000000,
      "rank": "5"
    }
  ],
  "boxes": [
    {
      "box_number": 1,
      "high_price": 35.34,
      "low_price": 35.34,
      "volume": 777747,
      "dollars": 27485578,
      "trades": 1,
      "date_range": "2025-08-18",
      "color": "blue"
    }
  ]
}