{
  "metadata": {
    "ticker": "FAS",
    "generated_at": "2026-02-12T01:37:06.748983+00:00Z",
    "date_range": "2025-11-13 to 2026-02-11",
    "source": "volumeleaders.com",
    "script": "populate_ticker_data.py"
  },
  "prints": [],
  "levels": [
    {
      "price": 159.9,
      "volume": 110076,
      "dollars": 17597172,
      "rank": 0
    },
    {
      "price": 147.3,
      "volume": 95095,
      "dollars": 14006694,
      "rank": 0
    },
    {
      "price": 170.1,
      "volume": 69751,
      "dollars": 11866737,
      "rank": 0
    },
    {
      "price": 147.5,
      "volume": 79595,
      "dollars": 11740262,
      "rank": 0
    },
    {
      "price": 176.0,
      "volume": 66238,
      "dollars": 11657564,
      "rank": 0
    }
  ],
  "boxes": []
}