{
  "metadata": {
    "ticker": "GDS",
    "generated_at": "2025-11-19T22:39:55.072097+00:00Z",
    "date_range": "2025-08-21 to 2025-11-19",
    "source": "volumeleaders.com",
    "script": "populate_ticker_data.py"
  },
  "prints": [],
  "levels": [
    {
      "price": 34.9,
      "volume": 7370000,
      "dollars": 260000000,
      "rank": "1"
    },
    {
      "price": 37.8,
      "volume": 5560000,
      "dollars": 210000000,
      "rank": "2"
    },
    {
      "price": 37.1,
      "volume": 3430000,
      "dollars": 130000000,
      "rank": "7"
    },
    {
      "price": 39.0,
      "volume": 2690000,
      "dollars": 100000000,
      "rank": "9"
    },
    {
      "price": 34.3,
      "volume": 2970000,
      "dollars": 100000000,
      "rank": "10"
    }
  ],
  "boxes": []
}