{
  "metadata": {
    "ticker": "HCA",
    "generated_at": "2025-12-25T10:57:49.126886+00:00Z",
    "date_range": "2025-09-26 to 2025-12-25",
    "source": "volumeleaders.com",
    "script": "populate_ticker_data.py"
  },
  "prints": [
    {
      "timestamp": 1766116800,
      "price": 472.98,
      "volume": 1350537,
      "dollars": 638776990,
      "rank": 6,
      "conditions": "",
      "exchange": "",
      "is_dark_pool": false,
      "relative_size": 0.0,
      "vcd": 0.0
    },
    {
      "timestamp": 1763956800,
      "price": 501.04,
      "volume": 1041534,
      "dollars": 521850195,
      "rank": 8,
      "conditions": "",
      "exchange": "",
      "is_dark_pool": false,
      "relative_size": 0.0,
      "vcd": 0.0
    }
  ],
  "levels": [
    {
      "price": 473.0,
      "volume": 2460000,
      "dollars": 1160000000,
      "rank": "3"
    },
    {
      "price": 501.0,
      "volume": 1250000,
      "dollars": 630000000,
      "rank": "10"
    },
    {
      "price": 486.8,
      "volume": 730000,
      "dollars": 360000000,
      "rank": "34"
    },
    {
      "price": 426.2,
      "volume": 620000,
      "dollars": 270000000,
      "rank": "74"
    },
    {
      "price": 472.0,
      "volume": 450000,
      "dollars": 210000000,
      "rank": "0"
    }
  ],
  "boxes": []
}