{
  "metadata": {
    "ticker": "HNGE",
    "generated_at": "2026-07-02T00:41:15.303637+00:00Z",
    "date_range": "2026-04-02 to 2026-07-01",
    "source": "volumeleaders.com",
    "script": "populate_ticker_data.py"
  },
  "prints": [
    {
      "timestamp": 1782446400,
      "price": 78.97,
      "volume": 4732643,
      "dollars": 373736817,
      "rank": 1,
      "conditions": "",
      "exchange": "",
      "is_dark_pool": false,
      "relative_size": 0.0,
      "vcd": 0.0
    },
    {
      "timestamp": 1781755200,
      "price": 69.42,
      "volume": 1270468,
      "dollars": 88195888,
      "rank": 2,
      "conditions": "",
      "exchange": "",
      "is_dark_pool": false,
      "relative_size": 0.0,
      "vcd": 0.0
    },
    {
      "timestamp": 1782100800,
      "price": 68.85,
      "volume": 607148,
      "dollars": 41802139,
      "rank": 6,
      "conditions": "",
      "exchange": "",
      "is_dark_pool": false,
      "relative_size": 0.0,
      "vcd": 0.0
    },
    {
      "timestamp": 1781064000,
      "price": 62.06,
      "volume": 671466,
      "dollars": 41671179,
      "rank": 7,
      "conditions": "",
      "exchange": "",
      "is_dark_pool": false,
      "relative_size": 0.0,
      "vcd": 0.0
    },
    {
      "timestamp": 1781668800,
      "price": 67.04,
      "volume": 621579,
      "dollars": 41670656,
      "rank": 8,
      "conditions": "",
      "exchange": "",
      "is_dark_pool": false,
      "relative_size": 0.0,
      "vcd": 0.0
    },
    {
      "timestamp": 1781582400,
      "price": 67.81,
      "volume": 580860,
      "dollars": 39388116,
      "rank": 9,
      "conditions": "",
      "exchange": "",
      "is_dark_pool": false,
      "relative_size": 0.0,
      "vcd": 0.0
    },
    {
      "timestamp": 1782792000,
      "price": 83.0,
      "volume": 443129,
      "dollars": 36779707,
      "rank": 11,
      "conditions": "",
      "exchange": "",
      "is_dark_pool": false,
      "relative_size": 0.0,
      "vcd": 0.0
    },
    {
      "timestamp": 1782705600,
      "price": 81.48,
      "volume": 447052,
      "dollars": 36425796,
      "rank": 12,
      "conditions": "",
      "exchange": "",
      "is_dark_pool": false,
      "relative_size": 0.0,
      "vcd": 0.0
    },
    {
      "timestamp": 1782446400,
      "price": 78.97,
      "volume": 456212,
      "dollars": 36027061,
      "rank": 13,
      "conditions": "",
      "exchange": "",
      "is_dark_pool": false,
      "relative_size": 0.0,
      "vcd": 0.0
    },
    {
      "timestamp": 1780027200,
      "price": 56.21,
      "volume": 480275,
      "dollars": 26996257,
      "rank": 14,
      "conditions": "",
      "exchange": "",
      "is_dark_pool": false,
      "relative_size": 0.0,
      "vcd": 0.0
    }
  ],
  "levels": [
    {
      "price": 79.0,
      "volume": 6522596,
      "dollars": 515088533,
      "rank": 1
    },
    {
      "price": 69.4,
      "volume": 1912405,
      "dollars": 132758624,
      "rank": 2
    },
    {
      "price": 47.3,
      "volume": 2016513,
      "dollars": 95385430,
      "rank": 3
    },
    {
      "price": 39.3,
      "volume": 2358663,
      "dollars": 92606853,
      "rank": 4
    },
    {
      "price": 56.9,
      "volume": 1277260,
      "dollars": 72688866,
      "rank": 5
    }
  ],
  "boxes": []
}