{
  "metadata": {
    "ticker": "HYG",
    "generated_at": "2026-03-12T00:42:49.503391+00:00Z",
    "date_range": "2025-12-11 to 2026-03-11",
    "source": "volumeleaders.com",
    "script": "populate_ticker_data.py"
  },
  "prints": [],
  "levels": [
    {
      "price": 79.4,
      "volume": 341373853,
      "dollars": 27102986585,
      "rank": 4
    },
    {
      "price": 80.9,
      "volume": 324042633,
      "dollars": 26212406441,
      "rank": 6
    },
    {
      "price": 80.8,
      "volume": 283845496,
      "dollars": 22933902557,
      "rank": 10
    },
    {
      "price": 80.2,
      "volume": 284646499,
      "dollars": 22826646658,
      "rank": 11
    },
    {
      "price": 79.5,
      "volume": 277326857,
      "dollars": 22044493588,
      "rank": 14
    }
  ],
  "boxes": [
    {
      "box_number": 1,
      "high_price": 81.19,
      "low_price": 79.54,
      "volume": 59425351,
      "dollars": 4780696734,
      "trades": 116,
      "date_range": "2025-12-11 to 2026-03-11",
      "color": "#FF6B6B"
    }
  ]
}