{
  "metadata": {
    "ticker": "IDR",
    "generated_at": "2026-04-11T00:39:01.968999+00:00Z",
    "date_range": "2026-01-10 to 2026-04-10",
    "source": "volumeleaders.com",
    "script": "populate_ticker_data.py"
  },
  "prints": [],
  "levels": [
    {
      "price": 45.9,
      "volume": 930647,
      "dollars": 42698076,
      "rank": 1
    },
    {
      "price": 30.9,
      "volume": 692674,
      "dollars": 21410553,
      "rank": 2
    },
    {
      "price": 33.8,
      "volume": 178574,
      "dollars": 6034015,
      "rank": 4
    },
    {
      "price": 32.1,
      "volume": 156057,
      "dollars": 5012550,
      "rank": 5
    },
    {
      "price": 26.7,
      "volume": 161511,
      "dollars": 4317189,
      "rank": 6
    }
  ],
  "boxes": []
}