{
  "metadata": {
    "ticker": "IOT",
    "generated_at": "2025-06-13T00:56:24.501889+00:00Z",
    "date_range": "2025-03-14 to 2025-06-12",
    "source": "volumeleaders.com",
    "script": "populate_ticker_data.py"
  },
  "prints": [
    {
      "timestamp": 1742529600,
      "price": 40.16,
      "volume": 3334855,
      "dollars": 133927776,
      "rank": 3,
      "conditions": "",
      "exchange": "",
      "is_dark_pool": false,
      "relative_size": 0.0,
      "vcd": 0.0
    },
    {
      "timestamp": 1748577600,
      "price": 46.54,
      "volume": 1901729,
      "dollars": 88506467,
      "rank": 5,
      "conditions": "",
      "exchange": "",
      "is_dark_pool": false,
      "relative_size": 0.0,
      "vcd": 0.0
    },
    {
      "timestamp": 1743652800,
      "price": 33.66,
      "volume": 1313141,
      "dollars": 44200326,
      "rank": 23,
      "conditions": "",
      "exchange": "",
      "is_dark_pool": false,
      "relative_size": 0.0,
      "vcd": 0.0
    },
    {
      "timestamp": 1743566400,
      "price": 38.0,
      "volume": 1121036,
      "dollars": 42599368,
      "rank": 25,
      "conditions": "",
      "exchange": "",
      "is_dark_pool": false,
      "relative_size": 0.0,
      "vcd": 0.0
    }
  ],
  "levels": [
    {
      "price": 34.6,
      "volume": 10140000,
      "dollars": 350000000,
      "rank": "1"
    },
    {
      "price": 40.2,
      "volume": 5080000,
      "dollars": 200000000,
      "rank": "3"
    },
    {
      "price": 47.7,
      "volume": 4099999,
      "dollars": 200000000,
      "rank": "4"
    },
    {
      "price": 46.5,
      "volume": 3580000,
      "dollars": 170000000,
      "rank": "5"
    },
    {
      "price": 33.7,
      "volume": 4550000,
      "dollars": 150000000,
      "rank": "7"
    }
  ],
  "boxes": [
    {
      "box_number": 1,
      "high_price": 41.02,
      "low_price": 41.02,
      "volume": 729057,
      "dollars": 29905918,
      "trades": 1,
      "date_range": "2025-06-10",
      "color": "blue"
    },
    {
      "box_number": 2,
      "high_price": 45.85,
      "low_price": 45.85,
      "volume": 437400,
      "dollars": 20054790,
      "trades": 1,
      "date_range": "2025-05-29",
      "color": "green"
    }
  ]
}