{
  "metadata": {
    "ticker": "JEPQ",
    "generated_at": "2025-06-28T01:11:23.951962+00:00Z",
    "date_range": "2025-03-29 to 2025-06-27",
    "source": "volumeleaders.com",
    "script": "populate_ticker_data.py"
  },
  "prints": [],
  "levels": [
    {
      "price": 52.4,
      "volume": 7590000,
      "dollars": 400000000,
      "rank": "1"
    },
    {
      "price": 52.6,
      "volume": 7170000,
      "dollars": 380000000,
      "rank": "2"
    },
    {
      "price": 52.8,
      "volume": 6320000,
      "dollars": 330000000,
      "rank": "3"
    },
    {
      "price": 52.7,
      "volume": 6080000,
      "dollars": 320000000,
      "rank": "4"
    },
    {
      "price": 51.1,
      "volume": 5800000,
      "dollars": 300000000,
      "rank": "5"
    }
  ],
  "boxes": [
    {
      "box_number": 1,
      "high_price": 49.61,
      "low_price": 46.98,
      "volume": 4614777,
      "dollars": 221183395,
      "trades": 4,
      "date_range": "2025-04-03 to 2025-04-10",
      "color": "blue"
    },
    {
      "box_number": 2,
      "high_price": 52.57,
      "low_price": 52.57,
      "volume": 2769822,
      "dollars": 145609542,
      "trades": 1,
      "date_range": "2025-06-05",
      "color": "green"
    },
    {
      "box_number": 3,
      "high_price": 52.32,
      "low_price": 52.32,
      "volume": 1622623,
      "dollars": 84895635,
      "trades": 1,
      "date_range": "2025-05-13",
      "color": "orange"
    },
    {
      "box_number": 4,
      "high_price": 49.73,
      "low_price": 49.73,
      "volume": 1260232,
      "dollars": 62671337,
      "trades": 1,
      "date_range": "2025-04-23",
      "color": "red"
    },
    {
      "box_number": 5,
      "high_price": 51.69,
      "low_price": 51.69,
      "volume": 1043886,
      "dollars": 53958467,
      "trades": 1,
      "date_range": "2025-05-08",
      "color": "purple"
    },
    {
      "box_number": 6,
      "high_price": 51.16,
      "low_price": 51.16,
      "volume": 374850,
      "dollars": 19177326,
      "trades": 1,
      "date_range": "2025-04-29",
      "color": "yellow"
    }
  ]
}