{
  "metadata": {
    "ticker": "MUU",
    "generated_at": "2025-09-17T03:07:30.510556+00:00Z",
    "date_range": "2025-06-18 to 2025-09-16",
    "source": "volumeleaders.com",
    "script": "populate_ticker_data.py"
  },
  "prints": [
    {
      "timestamp": 1757649600,
      "price": 37.17,
      "volume": 56152,
      "dollars": 2087169,
      "rank": 1,
      "conditions": "",
      "exchange": "",
      "is_dark_pool": false,
      "relative_size": 0.0,
      "vcd": 0.0
    },
    {
      "timestamp": 1757476800,
      "price": 29.76,
      "volume": 50701,
      "dollars": 1508861,
      "rank": 2,
      "conditions": "",
      "exchange": "",
      "is_dark_pool": false,
      "relative_size": 0.0,
      "vcd": 0.0
    },
    {
      "timestamp": 1757563200,
      "price": 34.69,
      "volume": 27598,
      "dollars": 957374,
      "rank": 4,
      "conditions": "",
      "exchange": "",
      "is_dark_pool": false,
      "relative_size": 0.0,
      "vcd": 0.0
    },
    {
      "timestamp": 1757649600,
      "price": 35.59,
      "volume": 16879,
      "dollars": 600723,
      "rank": 7,
      "conditions": "",
      "exchange": "",
      "is_dark_pool": false,
      "relative_size": 0.0,
      "vcd": 0.0
    },
    {
      "timestamp": 1755835200,
      "price": 22.09,
      "volume": 26934,
      "dollars": 594974,
      "rank": 8,
      "conditions": "",
      "exchange": "",
      "is_dark_pool": false,
      "relative_size": 0.0,
      "vcd": 0.0
    },
    {
      "timestamp": 1757563200,
      "price": 36.04,
      "volume": 15055,
      "dollars": 542582,
      "rank": 13,
      "conditions": "",
      "exchange": "",
      "is_dark_pool": false,
      "relative_size": 0.0,
      "vcd": 0.0
    },
    {
      "timestamp": 1756958400,
      "price": 23.26,
      "volume": 21783,
      "dollars": 506672,
      "rank": 16,
      "conditions": "",
      "exchange": "",
      "is_dark_pool": false,
      "relative_size": 0.0,
      "vcd": 0.0
    }
  ],
  "levels": [
    {
      "price": 37.2,
      "volume": 60000,
      "dollars": 0,
      "rank": "1"
    },
    {
      "price": 29.8,
      "volume": 50000,
      "dollars": 0,
      "rank": "2"
    },
    {
      "price": 23.3,
      "volume": 50000,
      "dollars": 0,
      "rank": "3"
    },
    {
      "price": 22.5,
      "volume": 50000,
      "dollars": 0,
      "rank": "5"
    },
    {
      "price": 34.7,
      "volume": 30000,
      "dollars": 0,
      "rank": "6"
    }
  ],
  "boxes": []
}