{
  "metadata": {
    "ticker": "NVDX",
    "generated_at": "2025-09-17T03:07:32.308336+00:00Z",
    "date_range": "2025-06-18 to 2025-09-16",
    "source": "volumeleaders.com",
    "script": "populate_ticker_data.py"
  },
  "prints": [
    {
      "timestamp": 1751256000,
      "price": 14.59,
      "volume": 1750000,
      "dollars": 25530575,
      "rank": 1,
      "conditions": "",
      "exchange": "",
      "is_dark_pool": false,
      "relative_size": 0.0,
      "vcd": 0.0
    },
    {
      "timestamp": 1750996800,
      "price": 14.55,
      "volume": 1750000,
      "dollars": 25466175,
      "rank": 2,
      "conditions": "",
      "exchange": "",
      "is_dark_pool": false,
      "relative_size": 0.0,
      "vcd": 0.0
    }
  ],
  "levels": [
    {
      "price": 14.6,
      "volume": 4059999,
      "dollars": 60000000,
      "rank": "1"
    },
    {
      "price": 12.3,
      "volume": 2400000,
      "dollars": 30000000,
      "rank": "2"
    },
    {
      "price": 12.0,
      "volume": 2420000,
      "dollars": 30000000,
      "rank": "3"
    },
    {
      "price": 17.5,
      "volume": 1660000,
      "dollars": 30000000,
      "rank": "4"
    },
    {
      "price": 18.4,
      "volume": 1450000,
      "dollars": 30000000,
      "rank": "5"
    }
  ],
  "boxes": []
}