{
  "metadata": {
    "ticker": "ORLA",
    "generated_at": "2026-04-11T00:43:31.311770+00:00Z",
    "date_range": "2026-01-10 to 2026-04-10",
    "source": "volumeleaders.com",
    "script": "populate_ticker_data.py"
  },
  "prints": [],
  "levels": [
    {
      "price": 14.2,
      "volume": 18260730,
      "dollars": 258999382,
      "rank": 1
    },
    {
      "price": 14.0,
      "volume": 1582413,
      "dollars": 22197033,
      "rank": 5
    },
    {
      "price": 13.1,
      "volume": 1093124,
      "dollars": 14318224,
      "rank": 9
    },
    {
      "price": 18.0,
      "volume": 708614,
      "dollars": 12736635,
      "rank": 10
    },
    {
      "price": 13.7,
      "volume": 671864,
      "dollars": 9200411,
      "rank": 14
    }
  ],
  "boxes": []
}