{
  "metadata": {
    "ticker": "PGR",
    "generated_at": "2026-04-11T00:43:31.420161+00:00Z",
    "date_range": "2026-01-10 to 2026-04-10",
    "source": "volumeleaders.com",
    "script": "populate_ticker_data.py"
  },
  "prints": [],
  "levels": [
    {
      "price": 206.0,
      "volume": 8980819,
      "dollars": 1850112221,
      "rank": 2
    },
    {
      "price": 208.3,
      "volume": 4838142,
      "dollars": 1007645221,
      "rank": 7
    },
    {
      "price": 207.0,
      "volume": 4109349,
      "dollars": 850530253,
      "rank": 9
    },
    {
      "price": 205.5,
      "volume": 3645569,
      "dollars": 749169634,
      "rank": 17
    },
    {
      "price": 208.0,
      "volume": 3241348,
      "dollars": 674192116,
      "rank": 25
    }
  ],
  "boxes": []
}