{
  "metadata": {
    "ticker": "PLTR",
    "generated_at": "2025-06-18T00:32:13.386405+00:00Z",
    "date_range": "2025-03-19 to 2025-06-17",
    "source": "volumeleaders.com",
    "script": "populate_ticker_data.py"
  },
  "prints": [
    {
      "timestamp": 1748577600,
      "price": 131.78,
      "volume": 14629324,
      "dollars": 1927852316,
      "rank": 3,
      "conditions": "",
      "exchange": "",
      "is_dark_pool": false,
      "relative_size": 0.0,
      "vcd": 0.0
    },
    {
      "timestamp": 1742529600,
      "price": 90.96,
      "volume": 12499226,
      "dollars": 1136929596,
      "rank": 6,
      "conditions": "",
      "exchange": "",
      "is_dark_pool": false,
      "relative_size": 0.0,
      "vcd": 0.0
    },
    {
      "timestamp": 1742788800,
      "price": 96.75,
      "volume": 8074672,
      "dollars": 781224516,
      "rank": 14,
      "conditions": "",
      "exchange": "",
      "is_dark_pool": false,
      "relative_size": 0.0,
      "vcd": 0.0
    },
    {
      "timestamp": 1742443200,
      "price": 87.39,
      "volume": 7976284,
      "dollars": 697047458,
      "rank": 15,
      "conditions": "",
      "exchange": "",
      "is_dark_pool": false,
      "relative_size": 0.0,
      "vcd": 0.0
    },
    {
      "timestamp": 1744171200,
      "price": 92.01,
      "volume": 7279563,
      "dollars": 669792591,
      "rank": 17,
      "conditions": "",
      "exchange": "",
      "is_dark_pool": false,
      "relative_size": 0.0,
      "vcd": 0.0
    },
    {
      "timestamp": 1742356800,
      "price": 86.1,
      "volume": 7423632,
      "dollars": 639174715,
      "rank": 18,
      "conditions": "",
      "exchange": "",
      "is_dark_pool": false,
      "relative_size": 0.0,
      "vcd": 0.0
    },
    {
      "timestamp": 1742875200,
      "price": 96.5,
      "volume": 6612872,
      "dollars": 638142148,
      "rank": 19,
      "conditions": "",
      "exchange": "",
      "is_dark_pool": false,
      "relative_size": 0.0,
      "vcd": 0.0
    },
    {
      "timestamp": 1746504000,
      "price": 108.86,
      "volume": 4874008,
      "dollars": 530584510,
      "rank": 24,
      "conditions": "",
      "exchange": "",
      "is_dark_pool": false,
      "relative_size": 0.0,
      "vcd": 0.0
    },
    {
      "timestamp": 1746676800,
      "price": 119.15,
      "volume": 4203207,
      "dollars": 500812114,
      "rank": 29,
      "conditions": "",
      "exchange": "",
      "is_dark_pool": false,
      "relative_size": 0.0,
      "vcd": 0.0
    }
  ],
  "levels": [
    {
      "price": 80.6,
      "volume": 162470000,
      "dollars": 13090000000,
      "rank": "2"
    },
    {
      "price": 131.8,
      "volume": 22020000,
      "dollars": 2900000000,
      "rank": "3"
    },
    {
      "price": 91.0,
      "volume": 18000000,
      "dollars": 1640000000,
      "rank": "7"
    },
    {
      "price": 84.9,
      "volume": 17390000,
      "dollars": 1480000000,
      "rank": "9"
    },
    {
      "price": 87.4,
      "volume": 14300000,
      "dollars": 1250000000,
      "rank": "11"
    }
  ],
  "boxes": [
    {
      "box_number": 1,
      "high_price": 126.35,
      "low_price": 126.35,
      "volume": 143654,
      "dollars": 18150682,
      "trades": 1,
      "date_range": "2025-05-20",
      "color": "blue"
    }
  ]
}