{
  "metadata": {
    "ticker": "QQQ",
    "generated_at": "2026-04-07T00:58:24.559706+00:00Z",
    "date_range": "2026-01-06 to 2026-04-06",
    "source": "volumeleaders.com",
    "script": "populate_ticker_data.py"
  },
  "prints": [
    {
      "timestamp": 1769659200,
      "price": 625.91,
      "volume": 2000000,
      "dollars": 1251820000,
      "rank": 11,
      "conditions": "",
      "exchange": "",
      "is_dark_pool": false,
      "relative_size": 0.0,
      "vcd": 0.0
    }
  ],
  "levels": [
    {
      "price": 616.4,
      "volume": 14714998,
      "dollars": 9070653239,
      "rank": 27
    },
    {
      "price": 609.3,
      "volume": 11288171,
      "dollars": 6878009610,
      "rank": 83
    },
    {
      "price": 626.2,
      "volume": 8788776,
      "dollars": 5503525924,
      "rank": 0
    },
    {
      "price": 612.1,
      "volume": 8777381,
      "dollars": 5372557155,
      "rank": 0
    },
    {
      "price": 621.0,
      "volume": 8334642,
      "dollars": 5175803343,
      "rank": 0
    }
  ],
  "boxes": [
    {
      "box_number": 1,
      "high_price": 620.84,
      "low_price": 560.24,
      "volume": 2535717,
      "dollars": 1529875647,
      "trades": 34,
      "date_range": "2026-01-06 to 2026-04-06",
      "color": "#FF6B6B"
    }
  ]
}