{
  "metadata": {
    "ticker": "SOXL",
    "generated_at": "2026-07-02T00:49:02.960346+00:00Z",
    "date_range": "2026-04-02 to 2026-07-01",
    "source": "volumeleaders.com",
    "script": "populate_ticker_data.py"
  },
  "prints": [
    {
      "timestamp": 1781150400,
      "price": 223.99,
      "volume": 1368274,
      "dollars": 306479693,
      "rank": 1,
      "conditions": "",
      "exchange": "",
      "is_dark_pool": false,
      "relative_size": 0.0,
      "vcd": 0.0
    },
    {
      "timestamp": 1782360000,
      "price": 252.61,
      "volume": 1146273,
      "dollars": 289560022,
      "rank": 2,
      "conditions": "",
      "exchange": "",
      "is_dark_pool": false,
      "relative_size": 0.0,
      "vcd": 0.0
    },
    {
      "timestamp": 1779249600,
      "price": 173.2,
      "volume": 1434258,
      "dollars": 248413485,
      "rank": 3,
      "conditions": "",
      "exchange": "",
      "is_dark_pool": false,
      "relative_size": 0.0,
      "vcd": 0.0
    },
    {
      "timestamp": 1782878400,
      "price": 217.55,
      "volume": 1087681,
      "dollars": 236625001,
      "rank": 5,
      "conditions": "",
      "exchange": "",
      "is_dark_pool": false,
      "relative_size": 0.0,
      "vcd": 0.0
    },
    {
      "timestamp": 1780372800,
      "price": 266.32,
      "volume": 867060,
      "dollars": 230915419,
      "rank": 6,
      "conditions": "",
      "exchange": "",
      "is_dark_pool": false,
      "relative_size": 0.0,
      "vcd": 0.0
    },
    {
      "timestamp": 1781496000,
      "price": 272.5,
      "volume": 772246,
      "dollars": 210437035,
      "rank": 7,
      "conditions": "",
      "exchange": "",
      "is_dark_pool": false,
      "relative_size": 0.0,
      "vcd": 0.0
    },
    {
      "timestamp": 1781582400,
      "price": 226.19,
      "volume": 823107,
      "dollars": 186178572,
      "rank": 8,
      "conditions": "",
      "exchange": "",
      "is_dark_pool": false,
      "relative_size": 0.0,
      "vcd": 0.0
    },
    {
      "timestamp": 1777953600,
      "price": 144.16,
      "volume": 1204616,
      "dollars": 173657442,
      "rank": 9,
      "conditions": "",
      "exchange": "",
      "is_dark_pool": false,
      "relative_size": 0.0,
      "vcd": 0.0
    },
    {
      "timestamp": 1782705600,
      "price": 236.52,
      "volume": 724690,
      "dollars": 171403678,
      "rank": 10,
      "conditions": "",
      "exchange": "",
      "is_dark_pool": false,
      "relative_size": 0.0,
      "vcd": 0.0
    },
    {
      "timestamp": 1782273600,
      "price": 229.57,
      "volume": 726645,
      "dollars": 166815892,
      "rank": 11,
      "conditions": "",
      "exchange": "",
      "is_dark_pool": false,
      "relative_size": 0.0,
      "vcd": 0.0
    }
  ],
  "levels": [
    {
      "price": 54.0,
      "volume": 10698260,
      "dollars": 577593449,
      "rank": 5
    },
    {
      "price": 47.2,
      "volume": 8275155,
      "dollars": 390772922,
      "rank": 30
    },
    {
      "price": 47.9,
      "volume": 8151865,
      "dollars": 390441753,
      "rank": 31
    },
    {
      "price": 46.8,
      "volume": 7693581,
      "dollars": 360053619,
      "rank": 41
    },
    {
      "price": 224.0,
      "volume": 1487565,
      "dollars": 333201419,
      "rank": 50
    }
  ],
  "boxes": []
}