{
  "metadata": {
    "ticker": "SQQQ",
    "generated_at": "2026-04-23T00:54:35.125714+00:00Z",
    "date_range": "2026-01-22 to 2026-04-22",
    "source": "volumeleaders.com",
    "script": "populate_ticker_data.py"
  },
  "prints": [],
  "levels": [
    {
      "price": 68.2,
      "volume": 3319170,
      "dollars": 226359364,
      "rank": 3
    },
    {
      "price": 68.0,
      "volume": 3270293,
      "dollars": 222338160,
      "rank": 5
    },
    {
      "price": 71.3,
      "volume": 2913286,
      "dollars": 207681096,
      "rank": 6
    },
    {
      "price": 70.7,
      "volume": 2931848,
      "dollars": 207252838,
      "rank": 7
    },
    {
      "price": 71.0,
      "volume": 2901096,
      "dollars": 205966403,
      "rank": 8
    }
  ],
  "boxes": []
}