{
  "metadata": {
    "ticker": "TLS",
    "generated_at": "2026-07-02T00:49:59.314487+00:00Z",
    "date_range": "2026-04-02 to 2026-07-01",
    "source": "volumeleaders.com",
    "script": "populate_ticker_data.py"
  },
  "prints": [
    {
      "timestamp": 1782446400,
      "price": 4.5,
      "volume": 1218537,
      "dollars": 5483416,
      "rank": 16,
      "conditions": "",
      "exchange": "",
      "is_dark_pool": false,
      "relative_size": 0.0,
      "vcd": 0.0
    }
  ],
  "levels": [
    {
      "price": 4.0,
      "volume": 6892010,
      "dollars": 27704502,
      "rank": 2
    },
    {
      "price": 5.2,
      "volume": 4214008,
      "dollars": 21889381,
      "rank": 3
    },
    {
      "price": 4.5,
      "volume": 4515519,
      "dollars": 20297026,
      "rank": 4
    },
    {
      "price": 4.7,
      "volume": 3136038,
      "dollars": 14616339,
      "rank": 9
    },
    {
      "price": 4.9,
      "volume": 1544491,
      "dollars": 7530882,
      "rank": 17
    }
  ],
  "boxes": []
}