{
  "metadata": {
    "ticker": "TSLQ",
    "generated_at": "2026-04-28T01:07:17.040711+00:00Z",
    "date_range": "2026-01-27 to 2026-04-27",
    "source": "volumeleaders.com",
    "script": "populate_ticker_data.py"
  },
  "prints": [],
  "levels": [
    {
      "price": 23.1,
      "volume": 1804501,
      "dollars": 41691351,
      "rank": 1
    },
    {
      "price": 18.5,
      "volume": 1512162,
      "dollars": 27961836,
      "rank": 2
    },
    {
      "price": 23.2,
      "volume": 1189967,
      "dollars": 27588446,
      "rank": 3
    },
    {
      "price": 23.0,
      "volume": 1185498,
      "dollars": 27267657,
      "rank": 4
    },
    {
      "price": 25.7,
      "volume": 1045810,
      "dollars": 26883529,
      "rank": 5
    }
  ],
  "boxes": []
}