{
  "metadata": {
    "ticker": "TWLO",
    "generated_at": "2026-02-24T01:48:11.419679+00:00Z",
    "date_range": "2025-11-25 to 2026-02-23",
    "source": "volumeleaders.com",
    "script": "populate_ticker_data.py"
  },
  "prints": [
    {
      "timestamp": 1766116800,
      "price": 141.74,
      "volume": 1946392,
      "dollars": 275881602,
      "rank": 8,
      "conditions": "",
      "exchange": "",
      "is_dark_pool": false,
      "relative_size": 0.0,
      "vcd": 0.0
    }
  ],
  "levels": [
    {
      "price": 105.1,
      "volume": 18389280,
      "dollars": 1931818224,
      "rank": 1
    },
    {
      "price": 107.9,
      "volume": 7108894,
      "dollars": 767212363,
      "rank": 3
    },
    {
      "price": 133.0,
      "volume": 3744538,
      "dollars": 497852079,
      "rank": 4
    },
    {
      "price": 106.5,
      "volume": 4476835,
      "dollars": 476784094,
      "rank": 5
    },
    {
      "price": 141.7,
      "volume": 2093427,
      "dollars": 296719331,
      "rank": 15
    }
  ],
  "boxes": [
    {
      "box_number": 1,
      "high_price": 126.0,
      "low_price": 126.0,
      "volume": 167289,
      "dollars": 21078414,
      "trades": 1,
      "date_range": "2025-11-25 to 2026-02-23",
      "color": "#FF6B6B"
    }
  ]
}