{
  "metadata": {
    "ticker": "ZSL",
    "generated_at": "2026-04-14T00:53:34.424171+00:00Z",
    "date_range": "2026-01-13 to 2026-04-13",
    "source": "volumeleaders.com",
    "script": "populate_ticker_data.py"
  },
  "prints": [],
  "levels": [
    {
      "price": 29.6,
      "volume": 970387,
      "dollars": 28722774,
      "rank": 4
    },
    {
      "price": 26.7,
      "volume": 919567,
      "dollars": 24536633,
      "rank": 6
    },
    {
      "price": 29.7,
      "volume": 559917,
      "dollars": 16629589,
      "rank": 19
    },
    {
      "price": 24.8,
      "volume": 567682,
      "dollars": 14074913,
      "rank": 30
    },
    {
      "price": 19.4,
      "volume": 653743,
      "dollars": 12684825,
      "rank": 34
    }
  ],
  "boxes": []
}